{
  "base_price": 2995,
  "beamstation_catalog_url": "https://beamstation.com/datasets",
  "beamstation_origin": "https://beamstation.com",
  "category_group_name": "Restaurants",
  "config_category": "sales",
  "config_description": "--High-Volume, Active targets--\n\nPopular restaurants sitting in the Top 30% of their local market for proven foot traffic and review volume within the last 90 days and a city-wide market scope.\n\nThese are the highest-velocity, actively transacting accounts for payment processing, POS systems, and supply chain sales.\n\nValidated by an \"Active Heartbeat\" signal.",
  "config_name": "Top 30% Active Restaurant Whales in Jacksonville, US",
  "export_job_id": "a086b383-86cf-4dfb-9d1c-41a1dac033e6",
  "github_org": "Beamstation-Datasets",
  "id_short": 364522,
  "location_name": "Jacksonville",
  "location_type": "city",
  "repo_name": "top-30-active-restaurant-whales-in-jacksonville-us-sample-364522",
  "sample_b2_path": "b2-export:BeamStation-ExportFiles/364522/beamstation_364522_restaurants-us-fl_SAMPLE_DIST.csv",
  "sample_pct": 9.7,
  "sample_records": 16,
  "sample_sha256": "3a853e417a31e5b1f52dc5cc0e44afd3c27838130e3ab57c10d510fa651be1a9",
  "sample_size_bytes": 82524,
  "total_records": 165,
  "updated_at": "2026-04-29T06:39:58.803618+00:00"
}